cacheds3storage/__init__.py
django_cacheds3storage-0.3.0.dist-info/METADATA
django_cacheds3storage-0.3.0.dist-info/WHEEL
django_cacheds3storage-0.3.0.dist-info/top_level.txt
django_cacheds3storage-0.3.0.dist-info/RECORD
