Metadata-Version: 2.1
Name: django-cacheds3storage
Version: 0.3.0
Summary: S3 cached storage
Home-page: https://github.com/ccnmtl/django-cacheds3storage
Author: Anders Pearson
Author-email: ctl-dev@columbia.edu
License: BSD
Platform: any
Requires-Dist: django-storages
Requires-Dist: python-dateutil
Requires-Dist: boto3
